{"id": 305292, "title": "Parenthood", "authors": "Agenda", "platforms": "Atari 8 bit", "release_date": "2022-02-11", "thumbnail": "https://media.demozoo.org/screens/t/2f/32/323f.304997.png", "url": "https://demozoo.org/graphics/305292/", "download_link": "https://files.scene.org/view/parties/2022/lovebyte22/executable_graphics_oldschool/parenthood.zip", "other_links": [{"link_class": "PouetProduction", "url": "https://www.pouet.net/prod.php?which=90971"}], "flavor": "oldschool", "category": "tiny_executable_graphics"}