{"id": 318974, "title": "Night Watch", "authors": "Blossom", "platforms": "TIC-80", "release_date": "2023-02-11", "thumbnail": "https://media.demozoo.org/screens/t/cf/d4/5421.320332.png", "url": "https://demozoo.org/graphics/318974/", "download_link": "https://files.scene.org/view/demos/groups/marqueedesign/marqueedesign_nightwatch.zip", "other_links": [{"link_class": "PouetProduction", "url": "https://www.pouet.net/prod.php?which=93752"}, {"link_class": "YoutubeVideo", "url": "https://www.youtube.com/watch?v=M-KzQ5j9Gro"}], "tags": ["cat"], "flavor": "fantasy", "category": "tiny_executable_graphics"}